{"appleSKU":"","appleTeamID":"","enableCodelessAutoInitialization":true,"products":[{"id":"donate-1","type":0,"storeIDs":[],"defaultDescription":{"googleLocale":4,"title":"$1","description":"Donate $1"},"screenshotPath":"","applePriceTier":1,"xiaomiPriceTier":0,"googlePrice":{"data":[100,0,0,131072],"num":1.0},"pricingTemplateID":"","descriptions":[],"udpPrice":{"data":[0,0,0,0],"num":0.0},"payouts":[]},{"id":"donate-5","type":0,"storeIDs":[],"defaultDescription":{"googleLocale":4,"title":"$5","description":"Donate $5"},"screenshotPath":"","applePriceTier":0,"xiaomiPriceTier":0,"googlePrice":{"data":[500,0,0,131072],"num":5.0},"pricingTemplateID":"","descriptions":[],"udpPrice":{"data":[0,0,0,0],"num":0.0},"payouts":[]},{"id":"donate-3","type":0,"storeIDs":[],"defaultDescription":{"googleLocale":4,"title":"$3","description":"Donate $3"},"screenshotPath":"","applePriceTier":0,"xiaomiPriceTier":0,"googlePrice":{"data":[300,0,0,131072],"num":3.0},"pricingTemplateID":"","descriptions":[],"udpPrice":{"data":[0,0,0,0],"num":0.0},"payouts":[]}]}